Metadata-Version: 2.1
Name: daidaideya
Version: 0.1.0
Summary: My short description for my project.
Home-page: https://github.com/duyixian1234/condition_chain
Author: Awesome Soul
Author-email: duyixian1234@outlook.com
License: MIT
Platform: UNKNOWN
Classifier: License :: OSI Approved :: MIT License
Classifier: Programming Language :: Python
Classifier: Programming Language :: Python :: 3
Classifier: Programming Language :: Python :: 3.6
Classifier: Programming Language :: Python :: Implementation :: CPython
Classifier: Programming Language :: Python :: Implementation :: PyPy
Requires-Python: >=3.6.0
License-File: LICENSE
